{
  "AFRANIO GALDINO DE ARAUJO": {
    "Notas": [
      8.29,
      8.36,
      8.58,
      8.91,
      8.93,
      9.28
    ],
    "Desvios": [
      2.41,
      1.98,
      1.74,
      2.56,
      2.99,
      1.78
    ],
    "Componentes": {
      "ADM0512 - ADMINISTRACAO ESTRATEGICA": {
        "Notas": [
          8.36,
          8.58,
          8.91,
          9.28
        ],
        "Desvios": [
          2.41,
          1.74,
          2.56,
          1.78
        ],
        "DesvioDeNotas": 0.34758991642451303,
        "MediaDeNotas": 8.7825,
        "MediaDeDesvios": 2.1225,
        "NotaMediana": 8.91
      },
      "ADM0535 - TOPICOS ESPECIAIS IV": {
        "Notas": [
          8.93
        ],
        "Desvios": [
          1.98
        ],
        "DesvioDeNotas": 0,
        "MediaDeNotas": 8.93,
        "MediaDeDesvios": 1.98,
        "NotaMediana": 8.93
      },
      "ADM0533 - TOPICOS ESPECIAIS II": {
        "Notas": [
          8.29
        ],
        "Desvios": [
          2.99
        ],
        "DesvioDeNotas": 0,
        "MediaDeNotas": 8.29,
        "MediaDeDesvios": 2.99,
        "NotaMediana": 8.29
      }
    },
    "DesvioDeNotas": 0.34826953163701635,
    "MediaDeNotas": 8.725,
    "MediaDeDesvios": 2.2433333333333336,
    "NotaMediana": 8.91
  },
  "ALINE GEHLEN RODRIGUES SILVA": {
    "Notas": [
      8.02,
      8.31,
      8.34,
      8.72,
      8.77,
      8.82,
      9.23,
      9.28,
      9.43,
      9.45,
      9.54,
      9.54,
      9.83
    ],
    "Desvios": [
      1.37,
      1.54,
      1.73,
      1.94,
      2.33,
      1.97,
      2.12,
      2.1,
      2.25,
      1.19,
      1.67,
      1.12,
      1.76
    ],
    "Componentes": {
      "ADM0073 - ESTUDOS ORGANIZACIONAIS CONTEMPORANEOS": {
        "Notas": [
          9.54
        ],
        "Desvios": [
          1.37
        ],
        "DesvioDeNotas": 0,
        "MediaDeNotas": 9.54,
        "MediaDeDesvios": 1.37,
        "NotaMediana": 9.54
      },
      "ADM0057 - MARKETING I": {
        "Notas": [
          8.77,
          9.23
        ],
        "Desvios": [
          1.54,
          2.12
        ],
        "DesvioDeNotas": 0.23000000000000043,
        "MediaDeNotas": 9,
        "MediaDeDesvios": 1.83,
        "NotaMediana": 9.23
      },
      "ADM0067 - NOVAS TECNOLOGIAS NA GESTÃO PÚBLICA": {
        "Notas": [
          9.43,
          9.45
        ],
        "Desvios": [
          1.73,
          1.67
        ],
        "DesvioDeNotas": 0.009999999999999787,
        "MediaDeNotas": 9.44,
        "MediaDeDesvios": 1.7,
        "NotaMediana": 9.45
      },
      "ADM0504 - ORGANIZACAO E PROCESSOS": {
        "Notas": [
          8.34,
          8.72
        ],
        "Desvios": [
          1.94,
          2.1
        ],
        "DesvioDeNotas": 0.1900000000000004,
        "MediaDeNotas": 8.530000000000001,
        "MediaDeDesvios": 2.02,
        "NotaMediana": 8.72
      },
      "ADM0075 - ORGANIZAÇÃO, PROCESSOS E SISTEMAS": {
        "Notas": [
          8.02,
          8.82
        ],
        "Desvios": [
          2.33,
          1.97
        ],
        "DesvioDeNotas": 0.40000000000000036,
        "MediaDeNotas": 8.42,
        "MediaDeDesvios": 2.15,
        "NotaMediana": 8.82
      },
      "ADM0045 - PLANEJAMENTO GOVERNAMENTAL": {
        "Notas": [
          8.31,
          9.83
        ],
        "Desvios": [
          2.25,
          1.12
        ],
        "DesvioDeNotas": 0.7599999999999998,
        "MediaDeNotas": 9.07,
        "MediaDeDesvios": 1.685,
        "NotaMediana": 9.83
      },
      "ADM0074 - TEORIA GERAL DAS ORGANIZAÇÕES": {
        "Notas": [
          9.28,
          9.54
        ],
        "Desvios": [
          1.19,
          1.76
        ],
        "DesvioDeNotas": 0.1299999999999999,
        "MediaDeNotas": 9.41,
        "MediaDeDesvios": 1.475,
        "NotaMediana": 9.54
      }
    },
    "DesvioDeNotas": 0.5421161691265094,
    "MediaDeNotas": 9.021538461538462,
    "MediaDeDesvios": 1.7761538461538464,
    "NotaMediana": 9.23
  },
  "ANA PATRICIA RODRIGUES LEITE": {
    "Notas": [
      9.04,
      9.08,
      9.48,
      9.56,
      9.56,
      9.57
    ],
    "Desvios": [
      1.79,
      1.47,
      1.27,
      1.3,
      0.8,
      1.02
    ],
    "Componentes": {
      "ADM0135 - OFICINA DE PROJETO II": {
        "Notas": [
          9.04,
          9.48,
          9.56,
          9.57
        ],
        "Desvios": [
          1.79,
          1.27,
          1.3,
          1.02
        ],
        "DesvioDeNotas": 0.21787324296480334,
        "MediaDeNotas": 9.4125,
        "MediaDeDesvios": 1.3450000000000002,
        "NotaMediana": 9.56
      },
      "ADM0170 - MARKETING DE VAREJO": {
        "Notas": [
          9.56
        ],
        "Desvios": [
          1.47
        ],
        "DesvioDeNotas": 0,
        "MediaDeNotas": 9.56,
        "MediaDeDesvios": 1.47,
        "NotaMediana": 9.56
      },
      "ADM0060 - MARKETING II": {
        "Notas": [
          9.08
        ],
        "Desvios": [
          0.8
        ],
        "DesvioDeNotas": 0,
        "MediaDeNotas": 9.08,
        "MediaDeDesvios": 0.8,
        "NotaMediana": 9.08
      }
    },
    "DesvioDeNotas": 0.2296676342505021,
    "MediaDeNotas": 9.381666666666668,
    "MediaDeDesvios": 1.2749999999999997,
    "NotaMediana": 9.56
  },
  "ANATALIA SARAIVA MARTINS RAMOS": {
    "Notas": [
      9.15,
      9.4,
      9.52,
      9.58
    ],
    "Desvios": [
      1.74,
      1.64,
      2.01,
      1.55
    ],
    "Componentes": {
      "ADM0058 - GESTÃO DE SISTEMA DE INFORMAÇÃO": {
        "Notas": [
          9.15,
          9.4,
          9.52,
          9.58
        ],
        "Desvios": [
          1.74,
          1.64,
          2.01,
          1.55
        ],
        "DesvioDeNotas": 0.16482945731876913,
        "MediaDeNotas": 9.4125,
        "MediaDeDesvios": 1.7349999999999999,
        "NotaMediana": 9.52
      }
    },
    "DesvioDeNotas": 0.16482945731876913,
    "MediaDeNotas": 9.4125,
    "MediaDeDesvios": 1.7349999999999999,
    "NotaMediana": 9.52
  },
  "ANDERSON LUIZ REZENDE MOL": {
    "Notas": [
      7.99,
      8.15,
      8.61,
      8.62,
      8.7
    ],
    "Desvios": [
      2.39,
      2.41,
      1.76,
      2.41,
      1.78
    ],
    "Componentes": {
      "ADM0416 - ADMINISTRACAO FINANCEIRA II": {
        "Notas": [
          7.99,
          8.15,
          8.61,
          8.7
        ],
        "Desvios": [
          2.39,
          2.41,
          1.76,
          2.41
        ],
        "DesvioDeNotas": 0.2996143354380757,
        "MediaDeNotas": 8.362499999999999,
        "MediaDeDesvios": 2.2425,
        "NotaMediana": 8.61
      },
      "ADM0404 - ORCAMENTO EMPRESARIAL": {
        "Notas": [
          8.62
        ],
        "Desvios": [
          1.78
        ],
        "DesvioDeNotas": 0,
        "MediaDeNotas": 8.62,
        "MediaDeDesvios": 1.78,
        "NotaMediana": 8.62
      }
    },
    "DesvioDeNotas": 0.28709580282546754,
    "MediaDeNotas": 8.413999999999998,
    "MediaDeDesvios": 2.15,
    "NotaMediana": 8.61
  },
  "ANNE EMILIA COSTA CARVALHO": {
    "Notas": [
      9.59,
      9.73,
      9.74,
      9.75,
      9.79,
      9.81,
      9.88,
      9.95
    ],
    "Desvios": [
      1.31,
      1.22,
      1.67,
      1.37,
      1.38,
      1.59,
      1.48,
      1.13
    ],
    "Componentes": {
      "ADM0068 - ADMINISTRAÇÃO DE MATERIAIS E PATRIMÔNIO": {
        "Notas": [
          9.59,
          9.73,
          9.74,
          9.75,
          9.79,
          9.81,
          9.88,
          9.95
        ],
        "Desvios": [
          1.31,
          1.22,
          1.67,
          1.37,
          1.38,
          1.59,
          1.48,
          1.13
        ],
        "DesvioDeNotas": 0.10062305898749048,
        "MediaDeNotas": 9.780000000000001,
        "MediaDeDesvios": 1.3937500000000003,
        "NotaMediana": 9.79
      }
    },
    "DesvioDeNotas": 0.10062305898749048,
    "MediaDeNotas": 9.780000000000001,
    "MediaDeDesvios": 1.3937500000000003,
    "NotaMediana": 9.79
  },
  "ANTONIO CARLOS FERREIRA": {
    "Notas": [
      8.57,
      8.69,
      9.14,
      9.19,
      9.24,
      9.25,
      9.27,
      9.29,
      9.48,
      9.51,
      9.68
    ],
    "Desvios": [
      1.6,
      2.11,
      1.79,
      2.03,
      1.83,
      1.66,
      1.96,
      1.73,
      2.27,
      1.43,
      1.42
    ],
    "Componentes": {
      "ADM0524 - CONSULTORIA EMPRESARIAL": {
        "Notas": [
          9.14,
          9.19,
          9.24,
          9.25,
          9.27,
          9.29,
          9.48,
          9.68
        ],
        "Desvios": [
          1.6,
          2.11,
          2.03,
          1.83,
          1.96,
          1.73,
          1.43,
          1.42
        ],
        "DesvioDeNotas": 0.1655105736803543,
        "MediaDeNotas": 9.3175,
        "MediaDeDesvios": 1.7637500000000002,
        "NotaMediana": 9.27
      },
      "ADM0135 - OFICINA DE PROJETO II": {
        "Notas": [
          8.57,
          8.69,
          9.51
        ],
        "Desvios": [
          1.79,
          1.66,
          2.27
        ],
        "DesvioDeNotas": 0.417718671941881,
        "MediaDeNotas": 8.923333333333334,
        "MediaDeDesvios": 1.906666666666667,
        "NotaMediana": 8.69
      }
    },
    "DesvioDeNotas": 0.3135717983608741,
    "MediaDeNotas": 9.209999999999999,
    "MediaDeDesvios": 1.8027272727272725,
    "NotaMediana": 9.25
  },
  "BRUNO LUAN DANTAS CARDOSO": {
    "Notas": [
      9.13,
      9.47,
      9.52,
      9.6,
      9.74,
      9.75
    ],
    "Desvios": [
      1.94,
      1.44,
      0.82,
      1.35,
      1.09,
      1.33
    ],
    "Componentes": {
      "ADM0062 - GESTÃO DE EMPREENDIMENTOS ECONÔMICO-SOLIDÁRIOS": {
        "Notas": [
          9.13,
          9.47,
          9.52,
          9.74
        ],
        "Desvios": [
          1.94,
          1.44,
          1.35,
          1.33
        ],
        "DesvioDeNotas": 0.21846052274953454,
        "MediaDeNotas": 9.465,
        "MediaDeDesvios": 1.5150000000000001,
        "NotaMediana": 9.52
      },
      "COP0036 - ELABORAÇÃO DE PROJETO II": {
        "Notas": [
          9.75
        ],
        "Desvios": [
          0.82
        ],
        "DesvioDeNotas": 0,
        "MediaDeNotas": 9.75,
        "MediaDeDesvios": 0.82,
        "NotaMediana": 9.75
      },
      "COP0035 - ELABORAÇÃO DE PROJETO I": {
        "Notas": [
          9.6
        ],
        "Desvios": [
          1.09
        ],
        "DesvioDeNotas": 0,
        "MediaDeNotas": 9.6,
        "MediaDeDesvios": 1.09,
        "NotaMediana": 9.6
      }
    },
    "DesvioDeNotas": 0.2085465575517049,
    "MediaDeNotas": 9.535,
    "MediaDeDesvios": 1.3283333333333334,
    "NotaMediana": 9.6
  },
  "CARLOS ALBERTO FREIRE MEDEIROS": {
    "Notas": [
      7.31,
      8.58,
      8.7,
      8.91,
      9,
      9.13,
      9.37,
      9.39,
      9.57
    ],
    "Desvios": [
      1.88,
      1.91,
      1.97,
      1.86,
      2.57,
      2.36,
      2,
      1.26,
      1.18
    ],
    "Componentes": {
      "ADM0501 - GESTAO EMPRESARIAL": {
        "Notas": [
          9.13,
          9.57
        ],
        "Desvios": [
          1.88,
          1.86
        ],
        "DesvioDeNotas": 0.21999999999999975,
        "MediaDeNotas": 9.350000000000001,
        "MediaDeDesvios": 1.87,
        "NotaMediana": 9.57
      },
      "ADM0078 - LOGÍSTICA EMPRESARIAL": {
        "Notas": [
          7.31,
          8.58,
          8.7,
          8.91,
          9,
          9.37
        ],
        "Desvios": [
          1.91,
          1.97,
          2.57,
          2.36,
          2,
          1.26
        ],
        "DesvioDeNotas": 0.6469608437404333,
        "MediaDeNotas": 8.645,
        "MediaDeDesvios": 2.0116666666666663,
        "NotaMediana": 8.91
      },
      "DTU1108 - TEORIA GERAL DA ADMINISTRAÇÃO": {
        "Notas": [
          9.39
        ],
        "Desvios": [
          1.18
        ],
        "DesvioDeNotas": 0,
        "MediaDeNotas": 9.39,
        "MediaDeDesvios": 1.18,
        "NotaMediana": 9.39
      }
    },
    "DesvioDeNotas": 0.6360662284020278,
    "MediaDeNotas": 8.884444444444446,
    "MediaDeDesvios": 1.8877777777777776,
    "NotaMediana": 9
  },
  "CARLOS DAVID CEQUEIRA FEITOR": {
    "Notas": [
      9.27,
      9.43,
      9.45,
      9.52,
      9.52,
      9.55,
      9.57,
      9.59,
      9.79,
      9.8
    ],
    "Desvios": [
      1.35,
      1.51,
      1.7,
      1.57,
      1.7,
      1.68,
      1.29,
      1.53,
      1.26,
      1.73
    ],
    "Componentes": {
      "ADM0425 - ADMINISTRACAO DA PRODUCAO II": {
        "Notas": [
          9.27,
          9.43,
          9.52,
          9.55,
          9.57,
          9.59,
          9.79
        ],
        "Desvios": [
          1.35,
          1.51,
          1.7,
          1.57,
          1.68,
          1.29,
          1.73
        ],
        "DesvioDeNotas": 0.1468165591505819,
        "MediaDeNotas": 9.531428571428572,
        "MediaDeDesvios": 1.5471428571428574,
        "NotaMediana": 9.55
      },
      "ADM0424 - ADMINISTRACAO DA PRODUCAO I": {
        "Notas": [
          9.45,
          9.52,
          9.8
        ],
        "Desvios": [
          1.7,
          1.53,
          1.26
        ],
        "DesvioDeNotas": 0.1512172829628507,
        "MediaDeNotas": 9.59,
        "MediaDeDesvios": 1.4966666666666668,
        "NotaMediana": 9.52
      }
    },
    "DesvioDeNotas": 0.15056227947264894,
    "MediaDeNotas": 9.549,
    "MediaDeDesvios": 1.532,
    "NotaMediana": 9.55
  },
  "CAROLINA DE SOUSA MARTINS MELO": {
    "Notas": [
      9.27,
      9.42,
      9.45,
      9.48,
      9.57,
      9.59,
      9.59,
      9.64,
      9.64,
      9.69,
      9.69,
      9.69,
      9.7,
      9.75,
      9.78,
      9.79,
      9.79
    ],
    "Desvios": [
      1.95,
      1.51,
      1.49,
      1.74,
      1.46,
      1.8,
      1.32,
      1.43,
      1.38,
      1.78,
      1.74,
      1.57,
      1.81,
      1.43,
      1.16,
      1.01,
      1.71
    ],
    "Componentes": {
      "ADM0523 - EMPREENDEDORISMO E PLANO DE NEGÓCIOS": {
        "Notas": [
          9.7,
          9.75,
          9.78
        ],
        "Desvios": [
          1.95,
          1.32,
          1.43
        ],
        "DesvioDeNotas": 0.032998316455372295,
        "MediaDeNotas": 9.743333333333332,
        "MediaDeDesvios": 1.5666666666666667,
        "NotaMediana": 9.75
      },
      "APS1001 - FUNDAMENTOS DA ADMINISTRAÇÃO PÚBLICA": {
        "Notas": [
          9.69
        ],
        "Desvios": [
          1.51
        ],
        "DesvioDeNotas": 0,
        "MediaDeNotas": 9.69,
        "MediaDeDesvios": 1.51,
        "NotaMediana": 9.69
      },
      "ADM0067 - NOVAS TECNOLOGIAS NA GESTÃO PÚBLICA": {
        "Notas": [
          9.45,
          9.59,
          9.79
        ],
        "Desvios": [
          1.49,
          1.81,
          1.43
        ],
        "DesvioDeNotas": 0.13952299690970893,
        "MediaDeNotas": 9.61,
        "MediaDeDesvios": 1.5766666666666664,
        "NotaMediana": 9.59
      },
      "ADM0135 - OFICINA DE PROJETO II": {
        "Notas": [
          9.27,
          9.69
        ],
        "Desvios": [
          1.74,
          1.16
        ],
        "DesvioDeNotas": 0.20999999999999996,
        "MediaDeNotas": 9.48,
        "MediaDeDesvios": 1.45,
        "NotaMediana": 9.69
      },
      "ADM0518 - SISTEMAS DE GESTAO DA QUALIDADE": {
        "Notas": [
          9.48,
          9.59,
          9.69
        ],
        "Desvios": [
          1.46,
          1.8,
          1.74
        ],
        "DesvioDeNotas": 0.08576453553512367,
        "MediaDeNotas": 9.586666666666668,
        "MediaDeDesvios": 1.6666666666666667,
        "NotaMediana": 9.59
      },
      "ADM0075 - ORGANIZAÇÃO, PROCESSOS E SISTEMAS": {
        "Notas": [
          9.64
        ],
        "Desvios": [
          1.38
        ],
        "DesvioDeNotas": 0,
        "MediaDeNotas": 9.64,
        "MediaDeDesvios": 1.38,
        "NotaMediana": 9.64
      },
      "ADM0054 - PODER, POLÍTICA E GESTÃO": {
        "Notas": [
          9.42,
          9.57
        ],
        "Desvios": [
          1.78,
          1.71
        ],
        "DesvioDeNotas": 0.07500000000000018,
        "MediaDeNotas": 9.495000000000001,
        "MediaDeDesvios": 1.745,
        "NotaMediana": 9.57
      },
      "ADM0066 - FUNDAMENTOS DA ADMINISTRAÇÃO PÚBLICA": {
        "Notas": [
          9.64
        ],
        "Desvios": [
          1.57
        ],
        "DesvioDeNotas": 0,
        "MediaDeNotas": 9.64,
        "MediaDeDesvios": 1.57,
        "NotaMediana": 9.64
      },
      "ADM0560 - PLANEJAMENTO, PROJETO E GESTAO EMPRESARIAL": {
        "Notas": [
          9.79
        ],
        "Desvios": [
          1.01
        ],
        "DesvioDeNotas": 0,
        "MediaDeNotas": 9.79,
        "MediaDeDesvios": 1.01,
        "NotaMediana": 9.79
      }
    },
    "DesvioDeNotas": 0.14089923759804132,
    "MediaDeNotas": 9.619411764705882,
    "MediaDeDesvios": 1.5464705882352943,
    "NotaMediana": 9.64
  },
  "DANIEL DE ARAUJO MARTINS": {
    "Notas": [
      9.62,
      9.64,
      9.64,
      9.64,
      9.65,
      9.67,
      9.79,
      9.84
    ],
    "Desvios": [
      1.71,
      1.58,
      1.55,
      1.76,
      1.72,
      1.85,
      1.2,
      1.14
    ],
    "Componentes": {
      "ADM0059 - GESTÃO DA TECNOLOGIA DA INFORMAÇÃO": {
        "Notas": [
          9.64,
          9.65,
          9.79,
          9.84
        ],
        "Desvios": [
          1.71,
          1.55,
          1.72,
          1.2
        ],
        "DesvioDeNotas": 0.08689073598491341,
        "MediaDeNotas": 9.73,
        "MediaDeDesvios": 1.545,
        "NotaMediana": 9.79
      },
      "ADM0058 - GESTÃO DE SISTEMA DE INFORMAÇÃO": {
        "Notas": [
          9.62,
          9.64,
          9.64,
          9.67
        ],
        "Desvios": [
          1.58,
          1.76,
          1.85,
          1.14
        ],
        "DesvioDeNotas": 0.017853571071357304,
        "MediaDeNotas": 9.6425,
        "MediaDeDesvios": 1.5824999999999998,
        "NotaMediana": 9.64
      }
    },
    "DesvioDeNotas": 0.0764750776397119,
    "MediaDeNotas": 9.686250000000001,
    "MediaDeDesvios": 1.56375,
    "NotaMediana": 9.65
  },
  "DINARA LESLYE MACEDO E SILVA CALAZANS": {
    "Notas": [
      9.16,
      9.3,
      9.34,
      9.37,
      9.39,
      9.47,
      9.48,
      9.52,
      9.54,
      9.54,
      9.55,
      9.63,
      9.64,
      9.69,
      9.71,
      9.76,
      9.89
    ],
    "Desvios": [
      1.81,
      1.46,
      1.68,
      1.67,
      1.75,
      1.81,
      0.84,
      1.23,
      1.69,
      1.8,
      1.13,
      0.9,
      1.07,
      1.03,
      1.39,
      1.18,
      1.17
    ],
    "Componentes": {
      "ADM0512 - ADMINISTRACAO ESTRATEGICA": {
        "Notas": [
          9.39,
          9.54
        ],
        "Desvios": [
          1.81,
          1.67
        ],
        "DesvioDeNotas": 0.07499999999999929,
        "MediaDeNotas": 9.465,
        "MediaDeDesvios": 1.74,
        "NotaMediana": 9.54
      },
      "ADM0500 - METODOLOGIA CIENTIFICA E PESQUISA EM ADMINISTRACAO": {
        "Notas": [
          9.54,
          9.69
        ],
        "Desvios": [
          1.46,
          1.75
        ],
        "DesvioDeNotas": 0.07500000000000018,
        "MediaDeNotas": 9.614999999999998,
        "MediaDeDesvios": 1.605,
        "NotaMediana": 9.69
      },
      "ADM0075 - ORGANIZAÇÃO, PROCESSOS E SISTEMAS": {
        "Notas": [
          9.37,
          9.76
        ],
        "Desvios": [
          1.68,
          1.81
        ],
        "DesvioDeNotas": 0.19500000000000028,
        "MediaDeNotas": 9.565,
        "MediaDeDesvios": 1.745,
        "NotaMediana": 9.76
      },
      "CST3166.1 - GESTÃO EM ALIMENTAÇÃO COLETIVA II - PRÁTICA I": {
        "Notas": [
          9.48
        ],
        "Desvios": [
          0.84
        ],
        "DesvioDeNotas": 0,
        "MediaDeNotas": 9.48,
        "MediaDeDesvios": 0.84,
        "NotaMediana": 9.48
      },
      "CST3166.0 - GESTÃO EM ALIMENTAÇÃO COLETIVA II - TEORIA": {
        "Notas": [
          9.3
        ],
        "Desvios": [
          1.23
        ],
        "DesvioDeNotas": 0,
        "MediaDeNotas": 9.3,
        "MediaDeDesvios": 1.23,
        "NotaMediana": 9.3
      },
      "CST3165.1 - VIGILÂNCIA E CONTROLE SANITÁRIO DE ALIMENTOS - PRÁTICA I": {
        "Notas": [
          9.52
        ],
        "Desvios": [
          1.69
        ],
        "DesvioDeNotas": 0,
        "MediaDeNotas": 9.52,
        "MediaDeDesvios": 1.69,
        "NotaMediana": 9.52
      },
      "CST3165.2 - VIGILÂNCIA E CONTROLE SANITÁRIO DE ALIMENTOS - PRÁTICA II": {
        "Notas": [
          9.63,
          9.89
        ],
        "Desvios": [
          1.8,
          1.13
        ],
        "DesvioDeNotas": 0.1299999999999999,
        "MediaDeNotas": 9.760000000000002,
        "MediaDeDesvios": 1.4649999999999999,
        "NotaMediana": 9.89
      },
      "CST3135.0 - ACOMPANHAMENTO DE ESTÁGIO SUPERVISIONADO EM ALIMENTAÇÃO COLETIVA - TEORIA": {
        "Notas": [
          9.71
        ],
        "Desvios": [
          0.9
        ],
        "DesvioDeNotas": 0,
        "MediaDeNotas": 9.71,
        "MediaDeDesvios": 0.9,
        "NotaMediana": 9.71
      },
      "CST3133.1 - GESTÃO EM ALIMENTAÇÃO COLETIVA I - PRÁTICA I": {
        "Notas": [
          9.47
        ],
        "Desvios": [
          1.07
        ],
        "DesvioDeNotas": 0,
        "MediaDeNotas": 9.47,
        "MediaDeDesvios": 1.07,
        "NotaMediana": 9.47
      },
      "CST3133.2 - GESTÃO EM ALIMENTAÇÃO COLETIVA I - PRÁTICA II": {
        "Notas": [
          9.16,
          9.34
        ],
        "Desvios": [
          1.03,
          1.39
        ],
        "DesvioDeNotas": 0.08999999999999986,
        "MediaDeNotas": 9.25,
        "MediaDeDesvios": 1.21,
        "NotaMediana": 9.34
      },
      "CST3133.0 - GESTÃO EM ALIMENTAÇÃO COLETIVA I - TEORIA": {
        "Notas": [
          9.55
        ],
        "Desvios": [
          1.18
        ],
        "DesvioDeNotas": 0,
        "MediaDeNotas": 9.55,
        "MediaDeDesvios": 1.18,
        "NotaMediana": 9.55
      },
      "CST3102 - LIDERANÇA E GESTÃO DE PESSOAS": {
        "Notas": [
          9.64
        ],
        "Desvios": [
          1.17
        ],
        "DesvioDeNotas": 0,
        "MediaDeNotas": 9.64,
        "MediaDeDesvios": 1.17,
        "NotaMediana": 9.64
      }
    },
    "DesvioDeNotas": 0.17830031817191921,
    "MediaDeNotas": 9.528235294117648,
    "MediaDeDesvios": 1.3888235294117646,
    "NotaMediana": 9.54
  },
  "EVANGELINA DE MELLO BASTOS": {
    "Notas": [
      9.11,
      9.18,
      9.22,
      9.29,
      9.3,
      9.32,
      9.37,
      9.46,
      9.58,
      9.65,
      9.66,
      9.72,
      9.82
    ],
    "Desvios": [
      1.8,
      1.37,
      1.78,
      1.53,
      2.26,
      1.6,
      1.57,
      1.6,
      1.93,
      1.6,
      1.62,
      2.06,
      2.05
    ],
    "Componentes": {
      "ADM0001 - INTRODUCAO A ADMINISTRACAO": {
        "Notas": [
          9.32
        ],
        "Desvios": [
          1.8
        ],
        "DesvioDeNotas": 0,
        "MediaDeNotas": 9.32,
        "MediaDeDesvios": 1.8,
        "NotaMediana": 9.32
      },
      "ADM0060 - MARKETING II": {
        "Notas": [
          9.72
        ],
        "Desvios": [
          1.37
        ],
        "DesvioDeNotas": 0,
        "MediaDeNotas": 9.72,
        "MediaDeDesvios": 1.37,
        "NotaMediana": 9.72
      },
      "ADM0135 - OFICINA DE PROJETO II": {
        "Notas": [
          9.18
        ],
        "Desvios": [
          1.78
        ],
        "DesvioDeNotas": 0,
        "MediaDeNotas": 9.18,
        "MediaDeDesvios": 1.78,
        "NotaMediana": 9.18
      },
      "ADM0560 - PLANEJAMENTO, PROJETO E GESTAO EMPRESARIAL": {
        "Notas": [
          9.66
        ],
        "Desvios": [
          1.53
        ],
        "DesvioDeNotas": 0,
        "MediaDeNotas": 9.66,
        "MediaDeDesvios": 1.53,
        "NotaMediana": 9.66
      },
      "ADM0541 - GESTAO DE PESSOAS I": {
        "Notas": [
          9.3,
          9.58
        ],
        "Desvios": [
          2.26,
          1.6
        ],
        "DesvioDeNotas": 0.13999999999999968,
        "MediaDeNotas": 9.440000000000001,
        "MediaDeDesvios": 1.93,
        "NotaMediana": 9.58
      },
      "ADM0542 - GESTAO DE PESSOAS II": {
        "Notas": [
          9.65,
          9.82
        ],
        "Desvios": [
          1.6,
          1.57
        ],
        "DesvioDeNotas": 0.08499999999999996,
        "MediaDeNotas": 9.735,
        "MediaDeDesvios": 1.585,
        "NotaMediana": 9.82
      },
      "ADM0059 - GESTÃO DA TECNOLOGIA DA INFORMAÇÃO": {
        "Notas": [
          9.37,
          9.46
        ],
        "Desvios": [
          1.6,
          1.62
        ],
        "DesvioDeNotas": 0.04500000000000082,
        "MediaDeNotas": 9.415,
        "MediaDeDesvios": 1.61,
        "NotaMediana": 9.46
      },
      "ADM0500 - METODOLOGIA CIENTIFICA E PESQUISA EM ADMINISTRACAO": {
        "Notas": [
          9.11,
          9.22,
          9.29
        ],
        "Desvios": [
          1.93,
          2.06,
          2.05
        ],
        "DesvioDeNotas": 0.07408703590297619,
        "MediaDeNotas": 9.206666666666665,
        "MediaDeDesvios": 2.013333333333333,
        "NotaMediana": 9.22
      }
    },
    "DesvioDeNotas": 0.21864564290139288,
    "MediaDeNotas": 9.436923076923076,
    "MediaDeDesvios": 1.7515384615384615,
    "NotaMediana": 9.37
  },
  "GABRIEL MARTINS DE ARAUJO FILHO": {
    "Notas": [
      6.9,
      7.62,
      9,
      9.04,
      9.04,
      9.09,
      9.12,
      9.21,
      9.29,
      9.29,
      9.3,
      9.32,
      9.41,
      9.56
    ],
    "Desvios": [
      1.57,
      1.82,
      2.75,
      1.6,
      1.54,
      1.26,
      2.69,
      1.95,
      1.03,
      1.62,
      1.43,
      1.44,
      1.8,
      1.41
    ],
    "Componentes": {
      "ADM0403 - ADMINISTRACAO FINANCEIRA I": {
        "Notas": [
          7.62,
          9,
          9.09,
          9.12,
          9.29,
          9.29
        ],
        "Desvios": [
          1.57,
          1.82,
          1.6,
          1.54,
          2.69,
          1.62
        ],
        "DesvioDeNotas": 0.5826782035471111,
        "MediaDeNotas": 8.901666666666666,
        "MediaDeDesvios": 1.8066666666666666,
        "NotaMediana": 9.12
      },
      "ADM0404 - ORCAMENTO EMPRESARIAL": {
        "Notas": [
          6.9,
          9.04,
          9.3
        ],
        "Desvios": [
          2.75,
          1.26,
          1.41
        ],
        "DesvioDeNotas": 1.0753397395965403,
        "MediaDeNotas": 8.413333333333334,
        "MediaDeDesvios": 1.8066666666666666,
        "NotaMediana": 9.04
      },
      "ADM0136 - ADMINISTRAÇÃO FINANCEIRA EM EMPREENDIMENTOS TURÍSTICOS": {
        "Notas": [
          9.21,
          9.32
        ],
        "Desvios": [
          1.95,
          1.43
        ],
        "DesvioDeNotas": 0.054999999999999716,
        "MediaDeNotas": 9.265,
        "MediaDeDesvios": 1.69,
        "NotaMediana": 9.32
      },
      "COP0009 - RELAÇÕES HUMANAS NAS ORGANIZAÇÕES": {
        "Notas": [
          9.56
        ],
        "Desvios": [
          1.03
        ],
        "DesvioDeNotas": 0,
        "MediaDeNotas": 9.56,
        "MediaDeDesvios": 1.03,
        "NotaMediana": 9.56
      },
      "ADM0422 - MATEMATICA FINANCEIRA": {
        "Notas": [
          9.04,
          9.41
        ],
        "Desvios": [
          1.44,
          1.8
        ],
        "DesvioDeNotas": 0.1850000000000005,
        "MediaDeNotas": 9.225,
        "MediaDeDesvios": 1.62,
        "NotaMediana": 9.41
      }
    },
    "DesvioDeNotas": 0.7161222817710531,
    "MediaDeNotas": 8.942142857142857,
    "MediaDeDesvios": 1.7078571428571432,
    "NotaMediana": 9.21
  },
  "HENRIQUE CLEMENTINO DE SOUZA": {
    "Notas": [
      8.94,
      9.08,
      9.09,
      9.09,
      9.15,
      9.18,
      9.23,
      9.24,
      9.28,
      9.29,
      9.31,
      9.43,
      9.5,
      9.58,
      9.7,
      9.82
    ],
    "Desvios": [
      2.09,
      1.76,
      2.43,
      1.53,
      1.81,
      1.88,
      2.21,
      1.9,
      2.16,
      1.26,
      1.91,
      1.98,
      1.23,
      1.92,
      2.28,
      1.89
    ],
    "Componentes": {
      "ADM0424 - ADMINISTRACAO DA PRODUCAO I": {
        "Notas": [
          9.18,
          9.7
        ],
        "Desvios": [
          2.09,
          1.76
        ],
        "DesvioDeNotas": 0.2599999999999998,
        "MediaDeNotas": 9.44,
        "MediaDeDesvios": 1.9249999999999998,
        "NotaMediana": 9.7
      },
      "ADM0136 - ADMINISTRAÇÃO FINANCEIRA EM EMPREENDIMENTOS TURÍSTICOS": {
        "Notas": [
          9.08,
          9.15,
          9.28
        ],
        "Desvios": [
          2.43,
          1.88,
          1.98
        ],
        "DesvioDeNotas": 0.08286535263104002,
        "MediaDeNotas": 9.17,
        "MediaDeDesvios": 2.096666666666667,
        "NotaMediana": 9.15
      },
      "ADM0073 - ESTUDOS ORGANIZACIONAIS CONTEMPORANEOS": {
        "Notas": [
          9.43
        ],
        "Desvios": [
          1.53
        ],
        "DesvioDeNotas": 0,
        "MediaDeNotas": 9.43,
        "MediaDeDesvios": 1.53,
        "NotaMediana": 9.43
      },
      "ADM0525 - JOGOS DE EMPRESAS": {
        "Notas": [
          9.29
        ],
        "Desvios": [
          1.81
        ],
        "DesvioDeNotas": 0,
        "MediaDeNotas": 9.29,
        "MediaDeDesvios": 1.81,
        "NotaMediana": 9.29
      },
      "ADM0541 - GESTAO DE PESSOAS I": {
        "Notas": [
          9.24
        ],
        "Desvios": [
          2.21
        ],
        "DesvioDeNotas": 0,
        "MediaDeNotas": 9.24,
        "MediaDeDesvios": 2.21,
        "NotaMediana": 9.24
      },
      "ADM0501 - GESTAO EMPRESARIAL": {
        "Notas": [
          9.82
        ],
        "Desvios": [
          1.9
        ],
        "DesvioDeNotas": 0,
        "MediaDeNotas": 9.82,
        "MediaDeDesvios": 1.9,
        "NotaMediana": 9.82
      },
      "ADM0078 - LOGÍSTICA EMPRESARIAL": {
        "Notas": [
          9.31
        ],
        "Desvios": [
          2.16
        ],
        "DesvioDeNotas": 0,
        "MediaDeNotas": 9.31,
        "MediaDeDesvios": 2.16,
        "NotaMediana": 9.31
      },
      "ADM0069 - NOÇÕES DE PESQUISA OPERACIONAL": {
        "Notas": [
          8.94,
          9.09,
          9.5,
          9.58
        ],
        "Desvios": [
          1.26,
          1.23,
          1.92,
          2.28
        ],
        "DesvioDeNotas": 0.2692930559817689,
        "MediaDeNotas": 9.2775,
        "MediaDeDesvios": 1.6724999999999999,
        "NotaMediana": 9.5
      },
      "ADM0074 - TEORIA GERAL DAS ORGANIZAÇÕES": {
        "Notas": [
          9.09,
          9.23
        ],
        "Desvios": [
          1.91,
          1.89
        ],
        "DesvioDeNotas": 0.07000000000000028,
        "MediaDeNotas": 9.16,
        "MediaDeDesvios": 1.9,
        "NotaMediana": 9.23
      }
    },
    "DesvioDeNotas": 0.2341398820683909,
    "MediaDeNotas": 9.306875,
    "MediaDeDesvios": 1.8900000000000006,
    "NotaMediana": 9.28
  },
  "JOACY PEDRO DE MACEDO MEDEIROS": {
    "Notas": [
      2.4,
      5.3,
      5.57,
      8.66
    ],
    "Desvios": [
      3.85,
      3.07,
      2.45,
      2.89
    ],
    "Componentes": {
      "ADM0561 - COMERCIALIZACAO E MARKETING": {
        "Notas": [
          2.4
        ],
        "Desvios": [
          3.85
        ],
        "DesvioDeNotas": 0,
        "MediaDeNotas": 2.4,
        "MediaDeDesvios": 3.85,
        "NotaMediana": 2.4
      },
      "ADM0520 - MARKETING DE VAREJO E SERVICOS": {
        "Notas": [
          5.3,
          5.57,
          8.66
        ],
        "Desvios": [
          3.07,
          2.45,
          2.89
        ],
        "DesvioDeNotas": 1.5242703172337904,
        "MediaDeNotas": 6.510000000000001,
        "MediaDeDesvios": 2.8033333333333332,
        "NotaMediana": 5.57
      }
    },
    "DesvioDeNotas": 2.2158110817486225,
    "MediaDeNotas": 5.4825,
    "MediaDeDesvios": 3.0650000000000004,
    "NotaMediana": 5.57
  },
  "JOAO HEITOR DE AVILA SANTOS": {
    "Notas": [
      7.92,
      8.84,
      8.87,
      8.9,
      9.06,
      9.08,
      9.23,
      9.26,
      9.39,
      9.43,
      9.44,
      9.52,
      9.52,
      9.61,
      9.61,
      9.63,
      9.63,
      9.65,
      9.7
    ],
    "Desvios": [
      2.06,
      1.49,
      2.71,
      1.39,
      1.36,
      1.54,
      2.02,
      1.91,
      2.03,
      1.62,
      1.04,
      1.8,
      2.34,
      2.27,
      1.84,
      0.99,
      1.14,
      0.97,
      1.4
    ],
    "Componentes": {
      "ADM0001 - INTRODUCAO A ADMINISTRACAO": {
        "Notas": [
          9.65
        ],
        "Desvios": [
          2.06
        ],
        "DesvioDeNotas": 0,
        "MediaDeNotas": 9.65,
        "MediaDeDesvios": 2.06,
        "NotaMediana": 9.65
      },
      "ADM0525 - JOGOS DE EMPRESAS": {
        "Notas": [
          9.52
        ],
        "Desvios": [
          1.49
        ],
        "DesvioDeNotas": 0,
        "MediaDeNotas": 9.52,
        "MediaDeDesvios": 1.49,
        "NotaMediana": 9.52
      },
      "ADM0165 - MODELOS PARA TOMADA DE DECISÃO": {
        "Notas": [
          7.92
        ],
        "Desvios": [
          2.71
        ],
        "DesvioDeNotas": 0,
        "MediaDeNotas": 7.92,
        "MediaDeDesvios": 2.71,
        "NotaMediana": 7.92
      },
      "ADM0069 - NOÇÕES DE PESQUISA OPERACIONAL": {
        "Notas": [
          9.08,
          9.61,
          9.61
        ],
        "Desvios": [
          1.39,
          1.36,
          2.03
        ],
        "DesvioDeNotas": 0.2498443960192465,
        "MediaDeNotas": 9.433333333333332,
        "MediaDeDesvios": 1.593333333333333,
        "NotaMediana": 9.61
      },
      "ADM0075 - ORGANIZAÇÃO, PROCESSOS E SISTEMAS": {
        "Notas": [
          8.87,
          9.39,
          9.43,
          9.52
        ],
        "Desvios": [
          1.54,
          1.62,
          1.84,
          1.4
        ],
        "DesvioDeNotas": 0.2541038173660524,
        "MediaDeNotas": 9.3025,
        "MediaDeDesvios": 1.6,
        "NotaMediana": 9.43
      },
      "ADM0523 - EMPREENDEDORISMO E PLANO DE NEGÓCIOS": {
        "Notas": [
          9.26,
          9.44
        ],
        "Desvios": [
          2.02,
          0.99
        ],
        "DesvioDeNotas": 0.08999999999999986,
        "MediaDeNotas": 9.35,
        "MediaDeDesvios": 1.505,
        "NotaMediana": 9.44
      },
      "ADM0541 - GESTAO DE PESSOAS I": {
        "Notas": [
          9.06,
          9.7
        ],
        "Desvios": [
          1.91,
          1.14
        ],
        "DesvioDeNotas": 0.3199999999999994,
        "MediaDeNotas": 9.379999999999999,
        "MediaDeDesvios": 1.525,
        "NotaMediana": 9.7
      },
      "ADM0045 - PLANEJAMENTO GOVERNAMENTAL": {
        "Notas": [
          9.63
        ],
        "Desvios": [
          1.04
        ],
        "DesvioDeNotas": 0,
        "MediaDeNotas": 9.63,
        "MediaDeDesvios": 1.04,
        "NotaMediana": 9.63
      },
      "ADM0103 - DESENVOLVIMENTO GERENCIAL E INTERPESSOAL": {
        "Notas": [
          9.23
        ],
        "Desvios": [
          1.8
        ],
        "DesvioDeNotas": 0,
        "MediaDeNotas": 9.23,
        "MediaDeDesvios": 1.8,
        "NotaMediana": 9.23
      },
      "ADM0422 - MATEMATICA FINANCEIRA": {
        "Notas": [
          8.84,
          8.9
        ],
        "Desvios": [
          2.34,
          2.27
        ],
        "DesvioDeNotas": 0.03000000000000025,
        "MediaDeNotas": 8.870000000000001,
        "MediaDeDesvios": 2.3049999999999997,
        "NotaMediana": 8.9
      },
      "ADM0542 - GESTAO DE PESSOAS II": {
        "Notas": [
          9.63
        ],
        "Desvios": [
          0.97
        ],
        "DesvioDeNotas": 0,
        "MediaDeNotas": 9.63,
        "MediaDeDesvios": 0.97,
        "NotaMediana": 9.63
      }
    },
    "DesvioDeNotas": 0.4229254402112024,
    "MediaDeNotas": 9.278421052631579,
    "MediaDeDesvios": 1.68,
    "NotaMediana": 9.43
  },
  "JOSE BOLIVAR VIEIRA DA ROCHA": {
    "Notas": [
      6.93,
      7.69,
      7.96,
      8.13,
      8.22,
      8.24,
      8.66,
      9.22,
      9.22,
      9.32
    ],
    "Desvios": [
      2.65,
      2.83,
      2.82,
      3.07,
      2.94,
      3.04,
      3.08,
      2.19,
      1.87,
      1.66
    ],
    "Componentes": {
      "ADM0523 - EMPREENDEDORISMO E PLANO DE NEGÓCIOS": {
        "Notas": [
          7.69,
          7.96,
          8.13,
          8.22,
          8.24,
          8.66,
          9.22,
          9.32
        ],
        "Desvios": [
          2.65,
          2.83,
          2.82,
          3.07,
          3.04,
          3.08,
          1.87,
          1.66
        ],
        "DesvioDeNotas": 0.5486118846689342,
        "MediaDeNotas": 8.430000000000001,
        "MediaDeDesvios": 2.6275000000000004,
        "NotaMediana": 8.24
      },
      "ADM0533 - TOPICOS ESPECIAIS II": {
        "Notas": [
          6.93
        ],
        "Desvios": [
          2.94
        ],
        "DesvioDeNotas": 0,
        "MediaDeNotas": 6.93,
        "MediaDeDesvios": 2.94,
        "NotaMediana": 6.93
      },
      "ADM0001 - INTRODUCAO A ADMINISTRACAO": {
        "Notas": [
          9.22
        ],
        "Desvios": [
          2.19
        ],
        "DesvioDeNotas": 0,
        "MediaDeNotas": 9.22,
        "MediaDeDesvios": 2.19,
        "NotaMediana": 9.22
      }
    },
    "DesvioDeNotas": 0.7232903981112982,
    "MediaDeNotas": 8.359,
    "MediaDeDesvios": 2.615,
    "NotaMediana": 8.24
  },
  "JOSE FLAVIO LOPES VIEIRA": {
    "Notas": [
      2.94,
      6.79,
      7.04,
      7.32,
      7.95,
      8.04,
      8.1,
      8.2,
      8.57,
      8.64,
      8.68,
      8.73,
      8.78,
      8.78,
      8.81,
      8.81,
      8.86,
      8.9
    ],
    "Desvios": [
      2.88,
      2.68,
      2.26,
      2.71,
      3.03,
      2.57,
      2.56,
      2.57,
      3.79,
      2.02,
      1.76,
      1.74,
      1.85,
      1.63,
      1.82,
      1.73,
      1.84,
      1.83
    ],
    "Componentes": {
      "ADM0403 - ADMINISTRACAO FINANCEIRA I": {
        "Notas": [
          6.79,
          7.32,
          8.1,
          8.57,
          8.78
        ],
        "Desvios": [
          2.88,
          2.56,
          2.57,
          1.76,
          1.74
        ],
        "DesvioDeNotas": 0.7524732553386864,
        "MediaDeNotas": 7.912000000000001,
        "MediaDeDesvios": 2.302,
        "NotaMediana": 8.1
      },
      "ADM0422 - MATEMATICA FINANCEIRA": {
        "Notas": [
          7.04,
          7.95,
          8.04,
          8.2,
          8.64,
          8.73,
          8.81,
          8.81,
          8.86
        ],
        "Desvios": [
          2.68,
          2.71,
          3.03,
          2.57,
          2.02,
          1.82,
          1.73,
          1.84,
          1.83
        ],
        "DesvioDeNotas": 0.568228783693051,
        "MediaDeNotas": 8.342222222222222,
        "MediaDeDesvios": 2.2477777777777774,
        "NotaMediana": 8.64
      },
      "ADM0510 - MERCADO FINANCEIRO": {
        "Notas": [
          8.68
        ],
        "Desvios": [
          2.26
        ],
        "DesvioDeNotas": 0,
        "MediaDeNotas": 8.68,
        "MediaDeDesvios": 2.26,
        "NotaMediana": 8.68
      },
      "ADM0136 - ADMINISTRAÇÃO FINANCEIRA EM EMPREENDIMENTOS TURÍSTICOS": {
        "Notas": [
          2.94,
          8.78,
          8.9
        ],
        "Desvios": [
          3.79,
          1.85,
          1.63
        ],
        "DesvioDeNotas": 2.7817180941920685,
        "MediaDeNotas": 6.873333333333332,
        "MediaDeDesvios": 2.4233333333333333,
        "NotaMediana": 8.78
      }
    },
    "DesvioDeNotas": 1.3807003054006084,
    "MediaDeNotas": 7.996666666666666,
    "MediaDeDesvios": 2.2927777777777774,
    "NotaMediana": 8.64
  },
  "LUCIANA BEZERRA DE SOUZA GIANASI": {
    "Notas": [
      9.36,
      9.36,
      9.56
    ],
    "Desvios": [
      1.71,
      1.51,
      1.69
    ],
    "Componentes": {
      "ADM0064 - COMPORTAMENTO ORGANIZACIONAL": {
        "Notas": [
          9.56
        ],
        "Desvios": [
          1.71
        ],
        "DesvioDeNotas": 0,
        "MediaDeNotas": 9.56,
        "MediaDeDesvios": 1.71,
        "NotaMediana": 9.56
      },
      "ADM0541 - GESTAO DE PESSOAS I": {
        "Notas": [
          9.36
        ],
        "Desvios": [
          1.51
        ],
        "DesvioDeNotas": 0,
        "MediaDeNotas": 9.36,
        "MediaDeDesvios": 1.51,
        "NotaMediana": 9.36
      },
      "ADM0542 - GESTAO DE PESSOAS II": {
        "Notas": [
          9.36
        ],
        "Desvios": [
          1.69
        ],
        "DesvioDeNotas": 0,
        "MediaDeNotas": 9.36,
        "MediaDeDesvios": 1.69,
        "NotaMediana": 9.36
      }
    },
    "DesvioDeNotas": 0.09428090415820685,
    "MediaDeNotas": 9.426666666666668,
    "MediaDeDesvios": 1.6366666666666667,
    "NotaMediana": 9.36
  },
  "LUCILA MOURA RAMOS VASCONCELOS": {
    "Notas": [
      9.69,
      9.76,
      9.78,
      9.82,
      9.9,
      9.99
    ],
    "Desvios": [
      1.71,
      1.95,
      1.53,
      0.62,
      1.54,
      1.42
    ],
    "Componentes": {
      "ADM0541 - GESTAO DE PESSOAS I": {
        "Notas": [
          9.78,
          9.82,
          9.99
        ],
        "Desvios": [
          1.71,
          1.95,
          0.62
        ],
        "DesvioDeNotas": 0.09104333522498467,
        "MediaDeNotas": 9.863333333333335,
        "MediaDeDesvios": 1.4266666666666667,
        "NotaMediana": 9.82
      },
      "ADM0542 - GESTAO DE PESSOAS II": {
        "Notas": [
          9.69,
          9.76,
          9.9
        ],
        "Desvios": [
          1.53,
          1.54,
          1.42
        ],
        "DesvioDeNotas": 0.08730533902472565,
        "MediaDeNotas": 9.783333333333333,
        "MediaDeDesvios": 1.4966666666666668,
        "NotaMediana": 9.76
      }
    },
    "DesvioDeNotas": 0.09775252199076817,
    "MediaDeNotas": 9.823333333333332,
    "MediaDeDesvios": 1.4616666666666667,
    "NotaMediana": 9.82
  },
  "MANOEL VERAS DE SOUSA NETO": {
    "Notas": [
      7.12,
      7.71,
      8.8,
      8.83,
      8.86,
      9.51
    ],
    "Desvios": [
      2.89,
      2.15,
      1.43,
      2.21,
      1.56,
      1.56
    ],
    "Componentes": {
      "ADM0059 - GESTÃO DA TECNOLOGIA DA INFORMAÇÃO": {
        "Notas": [
          7.12,
          7.71
        ],
        "Desvios": [
          2.89,
          2.21
        ],
        "DesvioDeNotas": 0.29499999999999993,
        "MediaDeNotas": 7.415,
        "MediaDeDesvios": 2.55,
        "NotaMediana": 7.71
      },
      "ADM0159 - GESTÃO DE PROJETOS": {
        "Notas": [
          8.83,
          8.86
        ],
        "Desvios": [
          2.15,
          1.43
        ],
        "DesvioDeNotas": 0.01499999999999968,
        "MediaDeNotas": 8.844999999999999,
        "MediaDeDesvios": 1.79,
        "NotaMediana": 8.86
      },
      "ADM0533 - TOPICOS ESPECIAIS II": {
        "Notas": [
          8.8,
          9.51
        ],
        "Desvios": [
          1.56,
          1.56
        ],
        "DesvioDeNotas": 0.35499999999999954,
        "MediaDeNotas": 9.155000000000001,
        "MediaDeDesvios": 1.56,
        "NotaMediana": 9.51
      }
    },
    "DesvioDeNotas": 0.8033558088142236,
    "MediaDeNotas": 8.471666666666668,
    "MediaDeDesvios": 1.9666666666666668,
    "NotaMediana": 8.83
  },
  "MARCELO RIQUE CARICIO": {
    "Notas": [
      8.8,
      8.89,
      8.98,
      9.15,
      9.3,
      9.36,
      9.38,
      9.42,
      9.53
    ],
    "Desvios": [
      2.11,
      1.77,
      2.01,
      1.8,
      1.75,
      1.6,
      2.35,
      2.19,
      1.13
    ],
    "Componentes": {
      "ADM0079 - EMPREENDEDORISMO": {
        "Notas": [
          8.89,
          8.98,
          9.15,
          9.3,
          9.36,
          9.38,
          9.42,
          9.53
        ],
        "Desvios": [
          2.11,
          1.77,
          2.01,
          1.8,
          1.75,
          1.6,
          2.19,
          1.13
        ],
        "DesvioDeNotas": 0.20954936769172053,
        "MediaDeNotas": 9.25125,
        "MediaDeDesvios": 1.795,
        "NotaMediana": 9.36
      },
      "ADM0001 - INTRODUCAO A ADMINISTRACAO": {
        "Notas": [
          8.8
        ],
        "Desvios": [
          2.35
        ],
        "DesvioDeNotas": 0,
        "MediaDeNotas": 8.8,
        "MediaDeDesvios": 2.35,
        "NotaMediana": 8.8
      }
    },
    "DesvioDeNotas": 0.24319377022560232,
    "MediaDeNotas": 9.20111111111111,
    "MediaDeDesvios": 1.8566666666666665,
    "NotaMediana": 9.3
  },
  "MARCO AURELIO DE ALBUQUERQUE OTHON": {
    "Notas": [
      8.57,
      8.8,
      8.85,
      8.87,
      8.9,
      8.92,
      8.92,
      9.06,
      9.1,
      9.24,
      9.26,
      9.3,
      9.55
    ],
    "Desvios": [
      1.73,
      2.02,
      2.29,
      2.1,
      2.26,
      2.29,
      2.32,
      1.99,
      1.92,
      1.51,
      1.7,
      1.84,
      2.2
    ],
    "Componentes": {
      "ADM0403 - ADMINISTRACAO FINANCEIRA I": {
        "Notas": [
          8.57,
          8.85,
          9.3
        ],
        "Desvios": [
          1.73,
          2.29,
          1.92
        ],
        "DesvioDeNotas": 0.3007028803025045,
        "MediaDeNotas": 8.906666666666666,
        "MediaDeDesvios": 1.9799999999999998,
        "NotaMediana": 8.85
      },
      "ADM0077 - ADMINISTRAÇÃO DE CUSTOS GERENCIAIS": {
        "Notas": [
          9.24
        ],
        "Desvios": [
          2.02
        ],
        "DesvioDeNotas": 0,
        "MediaDeNotas": 9.24,
        "MediaDeDesvios": 2.02,
        "NotaMediana": 9.24
      },
      "ADM0404 - ORCAMENTO EMPRESARIAL": {
        "Notas": [
          8.8,
          8.87,
          8.9,
          8.92,
          9.55
        ],
        "Desvios": [
          2.29,
          2.26,
          2.32,
          1.99,
          2.2
        ],
        "DesvioDeNotas": 0.2740364939200619,
        "MediaDeNotas": 9.008,
        "MediaDeDesvios": 2.2119999999999997,
        "NotaMediana": 8.9
      },
      "ADM0422 - MATEMATICA FINANCEIRA": {
        "Notas": [
          8.92,
          9.06,
          9.1
        ],
        "Desvios": [
          2.1,
          1.7,
          1.84
        ],
        "DesvioDeNotas": 0.0771722460186015,
        "MediaDeNotas": 9.026666666666666,
        "MediaDeDesvios": 1.88,
        "NotaMediana": 9.06
      },
      "ADM0136 - ADMINISTRAÇÃO FINANCEIRA EM EMPREENDIMENTOS TURÍSTICOS": {
        "Notas": [
          9.26
        ],
        "Desvios": [
          1.51
        ],
        "DesvioDeNotas": 0,
        "MediaDeNotas": 9.26,
        "MediaDeDesvios": 1.51,
        "NotaMediana": 9.26
      }
    },
    "DesvioDeNotas": 0.24953922033461426,
    "MediaDeNotas": 9.026153846153846,
    "MediaDeDesvios": 2.013076923076923,
    "NotaMediana": 8.92
  },
  "MARIA VALERIA PEREIRA DE ARAUJO": {
    "Notas": [
      9.12,
      9.28,
      9.28,
      9.34,
      9.57,
      9.63,
      9.71
    ],
    "Desvios": [
      1.7,
      1.58,
      1.5,
      1.49,
      0.84,
      1.72,
      1.08
    ],
    "Componentes": {
      "ADM0060 - MARKETING II": {
        "Notas": [
          9.12,
          9.28,
          9.28,
          9.63
        ],
        "Desvios": [
          1.7,
          1.58,
          1.49,
          1.08
        ],
        "DesvioDeNotas": 0.18646380345793717,
        "MediaDeNotas": 9.3275,
        "MediaDeDesvios": 1.4625000000000001,
        "NotaMediana": 9.28
      },
      "ADM0057 - MARKETING I": {
        "Notas": [
          9.34,
          9.57
        ],
        "Desvios": [
          1.5,
          1.72
        ],
        "DesvioDeNotas": 0.11500000000000021,
        "MediaDeNotas": 9.455,
        "MediaDeDesvios": 1.6099999999999999,
        "NotaMediana": 9.57
      },
      "COP0022 - OPERAÇÕES E LOGÍSTICA": {
        "Notas": [
          9.71
        ],
        "Desvios": [
          0.84
        ],
        "DesvioDeNotas": 0,
        "MediaDeNotas": 9.71,
        "MediaDeDesvios": 0.84,
        "NotaMediana": 9.71
      }
    },
    "DesvioDeNotas": 0.20223243850498793,
    "MediaDeNotas": 9.418571428571427,
    "MediaDeDesvios": 1.4157142857142857,
    "NotaMediana": 9.34
  },
  "PATRICIA WHEBBER SOUZA DE OLIVEIRA": {
    "Notas": [
      7.41,
      8.25,
      8.57,
      8.66,
      8.66,
      8.89,
      8.99,
      9.02,
      9.04,
      9.13,
      9.58
    ],
    "Desvios": [
      2.13,
      1.49,
      1.7,
      2.42,
      1.63,
      1.98,
      1.69,
      0.97,
      1.7,
      1.51,
      1.59
    ],
    "Componentes": {
      "ADM0064 - COMPORTAMENTO ORGANIZACIONAL": {
        "Notas": [
          8.25,
          8.66,
          8.66,
          9.04
        ],
        "Desvios": [
          2.13,
          1.7,
          1.98,
          1.7
        ],
        "DesvioDeNotas": 0.279407856009812,
        "MediaDeNotas": 8.6525,
        "MediaDeDesvios": 1.8775000000000002,
        "NotaMediana": 8.66
      },
      "ADM0103 - DESENVOLVIMENTO GERENCIAL E INTERPESSOAL": {
        "Notas": [
          7.41,
          8.89,
          8.99,
          9.13
        ],
        "Desvios": [
          1.49,
          2.42,
          1.69,
          1.51
        ],
        "DesvioDeNotas": 0.6951798328490264,
        "MediaDeNotas": 8.605,
        "MediaDeDesvios": 1.7774999999999999,
        "NotaMediana": 8.99
      },
      "ADM0512 - ADMINISTRACAO ESTRATEGICA": {
        "Notas": [
          8.57
        ],
        "Desvios": [
          1.63
        ],
        "DesvioDeNotas": 0,
        "MediaDeNotas": 8.57,
        "MediaDeDesvios": 1.63,
        "NotaMediana": 8.57
      },
      "COP0009 - RELAÇÕES HUMANAS NAS ORGANIZAÇÕES": {
        "Notas": [
          9.58
        ],
        "Desvios": [
          0.97
        ],
        "DesvioDeNotas": 0,
        "MediaDeNotas": 9.58,
        "MediaDeDesvios": 0.97,
        "NotaMediana": 9.58
      },
      "ADM0542 - GESTAO DE PESSOAS II": {
        "Notas": [
          9.02
        ],
        "Desvios": [
          1.59
        ],
        "DesvioDeNotas": 0,
        "MediaDeNotas": 9.02,
        "MediaDeDesvios": 1.59,
        "NotaMediana": 9.02
      }
    },
    "DesvioDeNotas": 0.5361031725053004,
    "MediaDeNotas": 8.745454545454544,
    "MediaDeDesvios": 1.7100000000000002,
    "NotaMediana": 8.89
  },
  "THELMA PIGNATARO": {
    "Notas": [
      7.06,
      8.49,
      8.98,
      9.07,
      9.09,
      9.14,
      9.39
    ],
    "Desvios": [
      2.07,
      2.07,
      3.15,
      1.74,
      2.06,
      1.45,
      1.23
    ],
    "Componentes": {
      "ADM0057 - MARKETING I": {
        "Notas": [
          8.98,
          9.09,
          9.14
        ],
        "Desvios": [
          2.07,
          2.07,
          1.74
        ],
        "DesvioDeNotas": 0.0668331255192114,
        "MediaDeNotas": 9.07,
        "MediaDeDesvios": 1.96,
        "NotaMediana": 9.09
      },
      "ADM0060 - MARKETING II": {
        "Notas": [
          7.06,
          8.49
        ],
        "Desvios": [
          3.15,
          2.06
        ],
        "DesvioDeNotas": 0.7150000000000003,
        "MediaDeNotas": 7.775,
        "MediaDeDesvios": 2.605,
        "NotaMediana": 8.49
      },
      "ADM0535 - TOPICOS ESPECIAIS IV": {
        "Notas": [
          9.07
        ],
        "Desvios": [
          1.45
        ],
        "DesvioDeNotas": 0,
        "MediaDeNotas": 9.07,
        "MediaDeDesvios": 1.45,
        "NotaMediana": 9.07
      },
      "ADM0537 - TOPICOS ESPECIAIS VI": {
        "Notas": [
          9.39
        ],
        "Desvios": [
          1.23
        ],
        "DesvioDeNotas": 0,
        "MediaDeNotas": 9.39,
        "MediaDeDesvios": 1.23,
        "NotaMediana": 9.39
      }
    },
    "DesvioDeNotas": 0.7325270768834059,
    "MediaDeNotas": 8.745714285714286,
    "MediaDeDesvios": 1.967142857142857,
    "NotaMediana": 9.07
  },
  "VALDEMIR GALVAO DE CARVALHO": {
    "Notas": [
      8.79,
      8.79,
      8.86,
      9.09,
      9.21,
      9.24,
      9.35,
      9.35,
      9.43,
      9.5,
      9.54,
      9.7,
      9.7,
      9.73
    ],
    "Desvios": [
      2.21,
      1.92,
      2.12,
      1.73,
      1.95,
      1.74,
      1.42,
      1.27,
      1.64,
      1.75,
      1.54,
      1.6,
      0.9,
      1.46
    ],
    "Componentes": {
      "ADM0422 - MATEMATICA FINANCEIRA": {
        "Notas": [
          8.79,
          9.21
        ],
        "Desvios": [
          2.21,
          1.92
        ],
        "DesvioDeNotas": 0.21000000000000085,
        "MediaDeNotas": 9,
        "MediaDeDesvios": 2.065,
        "NotaMediana": 9.21
      },
      "ADM0510 - MERCADO FINANCEIRO": {
        "Notas": [
          8.86,
          9.35
        ],
        "Desvios": [
          2.12,
          1.73
        ],
        "DesvioDeNotas": 0.2450000000000001,
        "MediaDeNotas": 9.105,
        "MediaDeDesvios": 1.925,
        "NotaMediana": 9.35
      },
      "ADM0134 - OFICINA DE PROJETO I": {
        "Notas": [
          9.09
        ],
        "Desvios": [
          1.95
        ],
        "DesvioDeNotas": 0,
        "MediaDeNotas": 9.09,
        "MediaDeDesvios": 1.95,
        "NotaMediana": 9.09
      },
      "ADM0403 - ADMINISTRACAO FINANCEIRA I": {
        "Notas": [
          9.73
        ],
        "Desvios": [
          1.74
        ],
        "DesvioDeNotas": 0,
        "MediaDeNotas": 9.73,
        "MediaDeDesvios": 1.74,
        "NotaMediana": 9.73
      },
      "ADM0077 - ADMINISTRAÇÃO DE CUSTOS GERENCIAIS": {
        "Notas": [
          9.43,
          9.7
        ],
        "Desvios": [
          1.42,
          1.27
        ],
        "DesvioDeNotas": 0.1349999999999998,
        "MediaDeNotas": 9.565,
        "MediaDeDesvios": 1.345,
        "NotaMediana": 9.7
      },
      "CSH5165 - ADMINISTRAÇÃO DE CUSTOS": {
        "Notas": [
          9.35
        ],
        "Desvios": [
          1.64
        ],
        "DesvioDeNotas": 0,
        "MediaDeNotas": 9.35,
        "MediaDeDesvios": 1.64,
        "NotaMediana": 9.35
      },
      "CSH5157 - ESTATÍSTICA DESCRITIVA": {
        "Notas": [
          9.24
        ],
        "Desvios": [
          1.75
        ],
        "DesvioDeNotas": 0,
        "MediaDeNotas": 9.24,
        "MediaDeDesvios": 1.75,
        "NotaMediana": 9.24
      },
      "CSH5144 - GESTÃO CONTÁBIL": {
        "Notas": [
          9.54
        ],
        "Desvios": [
          1.54
        ],
        "DesvioDeNotas": 0,
        "MediaDeNotas": 9.54,
        "MediaDeDesvios": 1.54,
        "NotaMediana": 9.54
      },
      "CSH5158 - ADMINISTRAÇÃO FINANCEIRA I": {
        "Notas": [
          8.79
        ],
        "Desvios": [
          1.6
        ],
        "DesvioDeNotas": 0,
        "MediaDeNotas": 8.79,
        "MediaDeDesvios": 1.6,
        "NotaMediana": 8.79
      },
      "CSH0510 - MERCADO DE CAPITAIS": {
        "Notas": [
          9.7
        ],
        "Desvios": [
          0.9
        ],
        "DesvioDeNotas": 0,
        "MediaDeNotas": 9.7,
        "MediaDeDesvios": 0.9,
        "NotaMediana": 9.7
      },
      "CSH5171 - PLANEJAMENTO ORÇAMENTÁRIO": {
        "Notas": [
          9.5
        ],
        "Desvios": [
          1.46
        ],
        "DesvioDeNotas": 0,
        "MediaDeNotas": 9.5,
        "MediaDeDesvios": 1.46,
        "NotaMediana": 9.5
      }
    },
    "DesvioDeNotas": 0.3154976632404813,
    "MediaDeNotas": 9.305714285714284,
    "MediaDeDesvios": 1.6607142857142858,
    "NotaMediana": 9.35
  },
  "VIDAL SUNCION INFANTE": {
    "Notas": [
      7.79,
      7.9,
      7.92,
      8.04,
      8.12,
      8.37,
      8.42,
      8.47,
      8.63,
      8.8,
      8.88,
      8.93,
      9.07,
      9.2
    ],
    "Desvios": [
      3.07,
      3.37,
      3.24,
      2.6,
      2.96,
      2.82,
      2.53,
      3.69,
      2.79,
      2.74,
      2.28,
      1.93,
      2.5,
      1.87
    ],
    "Componentes": {
      "ADM0001 - INTRODUCAO A ADMINISTRACAO": {
        "Notas": [
          7.79,
          7.9,
          8.37,
          8.42,
          8.8,
          9.07
        ],
        "Desvios": [
          3.07,
          2.6,
          3.69,
          2.79,
          1.93,
          2.5
        ],
        "DesvioDeNotas": 0.4531157566107021,
        "MediaDeNotas": 8.391666666666666,
        "MediaDeDesvios": 2.763333333333333,
        "NotaMediana": 8.42
      },
      "ADM0074 - TEORIA GERAL DAS ORGANIZAÇÕES": {
        "Notas": [
          7.92,
          8.04,
          8.47,
          8.63,
          8.93,
          9.2
        ],
        "Desvios": [
          3.37,
          3.24,
          2.96,
          2.82,
          2.74,
          1.87
        ],
        "DesvioDeNotas": 0.4536304173614855,
        "MediaDeNotas": 8.531666666666666,
        "MediaDeDesvios": 2.8333333333333335,
        "NotaMediana": 8.63
      },
      "ADM0512 - ADMINISTRACAO ESTRATEGICA": {
        "Notas": [
          8.12,
          8.88
        ],
        "Desvios": [
          2.53,
          2.28
        ],
        "DesvioDeNotas": 0.3800000000000008,
        "MediaDeNotas": 8.5,
        "MediaDeDesvios": 2.405,
        "NotaMediana": 8.88
      }
    },
    "DesvioDeNotas": 0.4485441301975693,
    "MediaDeNotas": 8.467142857142857,
    "MediaDeDesvios": 2.742142857142857,
    "NotaMediana": 8.47
  },
  "VINICIO DE SOUZA E ALMEIDA": {
    "Notas": [
      6.72,
      7.23,
      7.47,
      8.82,
      8.91,
      8.96
    ],
    "Desvios": [
      2.02,
      3.37,
      2.29,
      2.06,
      2.36,
      1.62
    ],
    "Componentes": {
      "ADM0416 - ADMINISTRACAO FINANCEIRA II": {
        "Notas": [
          6.72,
          8.82,
          8.91,
          8.96
        ],
        "Desvios": [
          2.02,
          3.37,
          2.06,
          1.62
        ],
        "DesvioDeNotas": 0.9438584374788417,
        "MediaDeNotas": 8.3525,
        "MediaDeDesvios": 2.2675,
        "NotaMediana": 8.91
      },
      "ADM0403 - ADMINISTRACAO FINANCEIRA I": {
        "Notas": [
          7.23,
          7.47
        ],
        "Desvios": [
          2.29,
          2.36
        ],
        "DesvioDeNotas": 0.11999999999999966,
        "MediaDeNotas": 7.35,
        "MediaDeDesvios": 2.325,
        "NotaMediana": 7.47
      }
    },
    "DesvioDeNotas": 0.906668198528118,
    "MediaDeNotas": 8.018333333333333,
    "MediaDeDesvios": 2.2866666666666666,
    "NotaMediana": 8.82
  },
  "CARLOS ALBERTO PEREIRA LEITE FILHO": {
    "Notas": [
      7.48,
      7.7,
      7.95,
      8.26,
      8.28,
      8.57,
      8.59,
      8.59,
      8.67,
      8.67,
      8.81,
      8.85,
      9,
      9.05,
      9.26,
      9.35,
      9.51,
      9.63
    ],
    "Desvios": [
      1.71,
      2.71,
      1.55,
      1.96,
      2.22,
      2.68,
      1.21,
      2.41,
      2.37,
      2.67,
      2.31,
      1.77,
      1.27,
      1.66,
      2.05,
      1.74,
      1.58,
      1.35
    ],
    "Componentes": {
      "ADM0001 - INTRODUCAO A ADMINISTRACAO": {
        "Notas": [
          9.63
        ],
        "Desvios": [
          1.71
        ],
        "DesvioDeNotas": 0,
        "MediaDeNotas": 9.63,
        "MediaDeDesvios": 1.71,
        "NotaMediana": 9.63
      },
      "ADM0078 - LOGÍSTICA EMPRESARIAL": {
        "Notas": [
          7.95
        ],
        "Desvios": [
          2.71
        ],
        "DesvioDeNotas": 0,
        "MediaDeNotas": 7.95,
        "MediaDeDesvios": 2.71,
        "NotaMediana": 7.95
      },
      "ADM0170 - MARKETING DE VAREJO": {
        "Notas": [
          9.51
        ],
        "Desvios": [
          1.55
        ],
        "DesvioDeNotas": 0,
        "MediaDeNotas": 9.51,
        "MediaDeDesvios": 1.55,
        "NotaMediana": 9.51
      },
      "ADM0057 - MARKETING I": {
        "Notas": [
          8.85
        ],
        "Desvios": [
          1.96
        ],
        "DesvioDeNotas": 0,
        "MediaDeNotas": 8.85,
        "MediaDeDesvios": 1.96,
        "NotaMediana": 8.85
      },
      "ADM0060 - MARKETING II": {
        "Notas": [
          8.67
        ],
        "Desvios": [
          2.22
        ],
        "DesvioDeNotas": 0,
        "MediaDeNotas": 8.67,
        "MediaDeDesvios": 2.22,
        "NotaMediana": 8.67
      },
      "ADM0069 - NOÇÕES DE PESQUISA OPERACIONAL": {
        "Notas": [
          8.26
        ],
        "Desvios": [
          2.68
        ],
        "DesvioDeNotas": 0,
        "MediaDeNotas": 8.26,
        "MediaDeDesvios": 2.68,
        "NotaMediana": 8.26
      },
      "ADM0064 - COMPORTAMENTO ORGANIZACIONAL": {
        "Notas": [
          9.05
        ],
        "Desvios": [
          1.21
        ],
        "DesvioDeNotas": 0,
        "MediaDeNotas": 9.05,
        "MediaDeDesvios": 1.21,
        "NotaMediana": 9.05
      },
      "ADM0075 - ORGANIZAÇÃO, PROCESSOS E SISTEMAS": {
        "Notas": [
          8.28
        ],
        "Desvios": [
          2.41
        ],
        "DesvioDeNotas": 0,
        "MediaDeNotas": 8.28,
        "MediaDeDesvios": 2.41,
        "NotaMediana": 8.28
      },
      "ADM0518 - SISTEMAS DE GESTAO DA QUALIDADE": {
        "Notas": [
          7.48,
          8.67,
          9,
          9.35
        ],
        "Desvios": [
          2.37,
          2.67,
          1.58,
          1.35
        ],
        "DesvioDeNotas": 0.7034379858949896,
        "MediaDeNotas": 8.625,
        "MediaDeDesvios": 1.9925000000000002,
        "NotaMediana": 9
      },
      "ADM0074 - TEORIA GERAL DAS ORGANIZAÇÕES": {
        "Notas": [
          7.7
        ],
        "Desvios": [
          2.31
        ],
        "DesvioDeNotas": 0,
        "MediaDeNotas": 7.7,
        "MediaDeDesvios": 2.31,
        "NotaMediana": 7.7
      },
      "ADM0425 - ADMINISTRACAO DA PRODUCAO II": {
        "Notas": [
          8.59
        ],
        "Desvios": [
          1.77
        ],
        "DesvioDeNotas": 0,
        "MediaDeNotas": 8.59,
        "MediaDeDesvios": 1.77,
        "NotaMediana": 8.59
      },
      "ADM0077 - ADMINISTRAÇÃO DE CUSTOS GERENCIAIS": {
        "Notas": [
          8.81
        ],
        "Desvios": [
          1.27
        ],
        "DesvioDeNotas": 0,
        "MediaDeNotas": 8.81,
        "MediaDeDesvios": 1.27,
        "NotaMediana": 8.81
      },
      "ADM0541 - GESTAO DE PESSOAS I": {
        "Notas": [
          9.26
        ],
        "Desvios": [
          1.66
        ],
        "DesvioDeNotas": 0,
        "MediaDeNotas": 9.26,
        "MediaDeDesvios": 1.66,
        "NotaMediana": 9.26
      },
      "ADM0054 - PODER, POLÍTICA E GESTÃO": {
        "Notas": [
          8.57,
          8.59
        ],
        "Desvios": [
          2.05,
          1.74
        ],
        "DesvioDeNotas": 0.009999999999999787,
        "MediaDeNotas": 8.58,
        "MediaDeDesvios": 1.895,
        "NotaMediana": 8.59
      }
    },
    "DesvioDeNotas": 0.5754214773044275,
    "MediaDeNotas": 8.67888888888889,
    "MediaDeDesvios": 1.9566666666666666,
    "NotaMediana": 8.67
  },
  "FRANCENILDO DANTAS RODRIGUES": {
    "Notas": [
      8.45,
      8.63,
      9,
      9.18,
      9.22,
      9.4,
      9.45,
      9.46,
      9.49,
      9.62,
      9.65,
      9.73,
      9.74
    ],
    "Desvios": [
      1.47,
      1.99,
      1.9,
      1.54,
      1.65,
      1.27,
      2.32,
      1.62,
      1.1,
      1.23,
      1.28,
      1.12,
      1.78
    ],
    "Componentes": {
      "ADM0424 - ADMINISTRACAO DA PRODUCAO I": {
        "Notas": [
          8.63,
          9.46,
          9.49
        ],
        "Desvios": [
          1.47,
          1.99,
          1.65
        ],
        "DesvioDeNotas": 0.3985250584621024,
        "MediaDeNotas": 9.193333333333333,
        "MediaDeDesvios": 1.7033333333333331,
        "NotaMediana": 9.46
      },
      "ADM0001 - INTRODUCAO A ADMINISTRACAO": {
        "Notas": [
          9
        ],
        "Desvios": [
          1.9
        ],
        "DesvioDeNotas": 0,
        "MediaDeNotas": 9,
        "MediaDeDesvios": 1.9,
        "NotaMediana": 9
      },
      "ADM0518 - SISTEMAS DE GESTAO DA QUALIDADE": {
        "Notas": [
          9.4
        ],
        "Desvios": [
          1.54
        ],
        "DesvioDeNotas": 0,
        "MediaDeNotas": 9.4,
        "MediaDeDesvios": 1.54,
        "NotaMediana": 9.4
      },
      "ADM0103 - DESENVOLVIMENTO GERENCIAL E INTERPESSOAL": {
        "Notas": [
          9.74
        ],
        "Desvios": [
          1.27
        ],
        "DesvioDeNotas": 0,
        "MediaDeNotas": 9.74,
        "MediaDeDesvios": 1.27,
        "NotaMediana": 9.74
      },
      "ADM0523 - EMPREENDEDORISMO E PLANO DE NEGÓCIOS": {
        "Notas": [
          9.22,
          9.65,
          9.73
        ],
        "Desvios": [
          2.32,
          1.1,
          1.23
        ],
        "DesvioDeNotas": 0.22395436042987754,
        "MediaDeNotas": 9.533333333333333,
        "MediaDeDesvios": 1.55,
        "NotaMediana": 9.65
      },
      "ADM0541 - GESTAO DE PESSOAS I": {
        "Notas": [
          9.18
        ],
        "Desvios": [
          1.62
        ],
        "DesvioDeNotas": 0,
        "MediaDeNotas": 9.18,
        "MediaDeDesvios": 1.62,
        "NotaMediana": 9.18
      },
      "ADM0059 - GESTÃO DA TECNOLOGIA DA INFORMAÇÃO": {
        "Notas": [
          9.62
        ],
        "Desvios": [
          1.28
        ],
        "DesvioDeNotas": 0,
        "MediaDeNotas": 9.62,
        "MediaDeDesvios": 1.28,
        "NotaMediana": 9.62
      },
      "ADM0058 - GESTÃO DE SISTEMA DE INFORMAÇÃO": {
        "Notas": [
          9.45
        ],
        "Desvios": [
          1.12
        ],
        "DesvioDeNotas": 0,
        "MediaDeNotas": 9.45,
        "MediaDeDesvios": 1.12,
        "NotaMediana": 9.45
      },
      "ADM0075 - ORGANIZAÇÃO, PROCESSOS E SISTEMAS": {
        "Notas": [
          8.45
        ],
        "Desvios": [
          1.78
        ],
        "DesvioDeNotas": 0,
        "MediaDeNotas": 8.45,
        "MediaDeDesvios": 1.78,
        "NotaMediana": 8.45
      }
    },
    "DesvioDeNotas": 0.39013728428812855,
    "MediaDeNotas": 9.309230769230771,
    "MediaDeDesvios": 1.5592307692307692,
    "NotaMediana": 9.45
  },
  "JUAREZ AZEVEDO DE PAIVA": {
    "Notas": [
      9.73,
      9.78,
      9.86
    ],
    "Desvios": [
      0.52,
      0.44,
      1.1
    ],
    "Componentes": {
      "COP0001 - COMUNICAÇÃO E EXPRESSÃO": {
        "Notas": [
          9.78
        ],
        "Desvios": [
          0.52
        ],
        "DesvioDeNotas": 0,
        "MediaDeNotas": 9.78,
        "MediaDeDesvios": 0.52,
        "NotaMediana": 9.78
      },
      "COP0012 - MOVIMENTOS SOCIAIS E PARTICIPAÇÃO": {
        "Notas": [
          9.86
        ],
        "Desvios": [
          0.44
        ],
        "DesvioDeNotas": 0,
        "MediaDeNotas": 9.86,
        "MediaDeDesvios": 0.44,
        "NotaMediana": 9.86
      },
      "COP0005 - FUNDAMENTOS DA GESTÃO SOCIAL": {
        "Notas": [
          9.73
        ],
        "Desvios": [
          1.1
        ],
        "DesvioDeNotas": 0,
        "MediaDeNotas": 9.73,
        "MediaDeDesvios": 1.1,
        "NotaMediana": 9.73
      }
    },
    "DesvioDeNotas": 0.053541261347363,
    "MediaDeNotas": 9.790000000000001,
    "MediaDeDesvios": 0.6866666666666666,
    "NotaMediana": 9.78
  },
  "MATILDE MEDEIROS DE ARAÚJO": {
    "Notas": [
      9.07,
      9.32,
      9.37,
      9.55,
      9.65
    ],
    "Desvios": [
      1.44,
      1.24,
      0.84,
      1.22,
      1.26
    ],
    "Componentes": {
      "ADM0134 - OFICINA DE PROJETO I": {
        "Notas": [
          9.07,
          9.32,
          9.37,
          9.55
        ],
        "Desvios": [
          1.44,
          1.24,
          1.22,
          1.26
        ],
        "DesvioDeNotas": 0.17151894939043916,
        "MediaDeNotas": 9.3275,
        "MediaDeDesvios": 1.2899999999999998,
        "NotaMediana": 9.37
      },
      "COP0020 - QUALIDADE ORGANIZACIONAL": {
        "Notas": [
          9.65
        ],
        "Desvios": [
          0.84
        ],
        "DesvioDeNotas": 0,
        "MediaDeNotas": 9.65,
        "MediaDeDesvios": 0.84,
        "NotaMediana": 9.65
      }
    },
    "DesvioDeNotas": 0.2004395170618809,
    "MediaDeNotas": 9.392,
    "MediaDeDesvios": 1.1999999999999997,
    "NotaMediana": 9.37
  },
  "MILENA CRISTINA DUARTE DE ALMEIDA": {
    "Notas": [
      9.31,
      9.32,
      9.41,
      9.59,
      9.71,
      9.72
    ],
    "Desvios": [
      1.48,
      1.55,
      1.64,
      1.19,
      1.86,
      1.46
    ],
    "Componentes": {
      "ADM0542 - GESTAO DE PESSOAS II": {
        "Notas": [
          9.41
        ],
        "Desvios": [
          1.48
        ],
        "DesvioDeNotas": 0,
        "MediaDeNotas": 9.41,
        "MediaDeDesvios": 1.48,
        "NotaMediana": 9.41
      },
      "ADM0078 - LOGÍSTICA EMPRESARIAL": {
        "Notas": [
          9.32
        ],
        "Desvios": [
          1.55
        ],
        "DesvioDeNotas": 0,
        "MediaDeNotas": 9.32,
        "MediaDeDesvios": 1.55,
        "NotaMediana": 9.32
      },
      "ADM0075 - ORGANIZAÇÃO, PROCESSOS E SISTEMAS": {
        "Notas": [
          9.59
        ],
        "Desvios": [
          1.64
        ],
        "DesvioDeNotas": 0,
        "MediaDeNotas": 9.59,
        "MediaDeDesvios": 1.64,
        "NotaMediana": 9.59
      },
      "ADM0045 - PLANEJAMENTO GOVERNAMENTAL": {
        "Notas": [
          9.72
        ],
        "Desvios": [
          1.19
        ],
        "DesvioDeNotas": 0,
        "MediaDeNotas": 9.72,
        "MediaDeDesvios": 1.19,
        "NotaMediana": 9.72
      },
      "ADM0054 - PODER, POLÍTICA E GESTÃO": {
        "Notas": [
          9.31
        ],
        "Desvios": [
          1.86
        ],
        "DesvioDeNotas": 0,
        "MediaDeNotas": 9.31,
        "MediaDeDesvios": 1.86,
        "NotaMediana": 9.31
      },
      "ADM0518 - SISTEMAS DE GESTAO DA QUALIDADE": {
        "Notas": [
          9.71
        ],
        "Desvios": [
          1.46
        ],
        "DesvioDeNotas": 0,
        "MediaDeNotas": 9.71,
        "MediaDeDesvios": 1.46,
        "NotaMediana": 9.71
      }
    },
    "DesvioDeNotas": 0.1715614564327704,
    "MediaDeNotas": 9.51,
    "MediaDeDesvios": 1.53,
    "NotaMediana": 9.59
  },
  "RUAN RODRIGO ARAUJO DA COSTA": {
    "Notas": [
      8.5,
      8.78,
      8.81,
      9.16
    ],
    "Desvios": [
      1.9,
      1.91,
      2.11,
      2.29
    ],
    "Componentes": {
      "ADM0403 - ADMINISTRACAO FINANCEIRA I": {
        "Notas": [
          8.78,
          8.81,
          9.16
        ],
        "Desvios": [
          1.9,
          1.91,
          2.11
        ],
        "DesvioDeNotas": 0.1724979871058083,
        "MediaDeNotas": 8.916666666666666,
        "MediaDeDesvios": 1.9733333333333334,
        "NotaMediana": 8.81
      },
      "ADM0422 - MATEMATICA FINANCEIRA": {
        "Notas": [
          8.5
        ],
        "Desvios": [
          2.29
        ],
        "DesvioDeNotas": 0,
        "MediaDeNotas": 8.5,
        "MediaDeDesvios": 2.29,
        "NotaMediana": 8.5
      }
    },
    "DesvioDeNotas": 0.23424079490985347,
    "MediaDeNotas": 8.8125,
    "MediaDeDesvios": 2.0525,
    "NotaMediana": 8.81
  },
  "ABDON SILVA RIBEIRO DA CUNHA": {
    "Notas": [
      9.73
    ],
    "Desvios": [
      1.16
    ],
    "Componentes": {
      "COP0017 - METODOLOGIAS DE SERVIÇO DE ASSISTÊNCIA TÉCNICA E EXTENSÃO RURAL": {
        "Notas": [
          9.73
        ],
        "Desvios": [
          1.16
        ],
        "DesvioDeNotas": 0,
        "MediaDeNotas": 9.73,
        "MediaDeDesvios": 1.16,
        "NotaMediana": 9.73
      }
    },
    "DesvioDeNotas": 0,
    "MediaDeNotas": 9.73,
    "MediaDeDesvios": 1.16,
    "NotaMediana": 9.73
  },
  "DALVANIR AVELINO DA SILVA": {
    "Notas": [
      9.87,
      9.89,
      9.9,
      9.95
    ],
    "Desvios": [
      1.27,
      1.15,
      0.9,
      1.09
    ],
    "Componentes": {
      "ADM0055 - FILOSOFIA E ÉTICA NAS ORGANIZAÇÕES": {
        "Notas": [
          9.89
        ],
        "Desvios": [
          1.27
        ],
        "DesvioDeNotas": 0,
        "MediaDeNotas": 9.89,
        "MediaDeDesvios": 1.27,
        "NotaMediana": 9.89
      },
      "ADM0066 - FUNDAMENTOS DA ADMINISTRAÇÃO PÚBLICA": {
        "Notas": [
          9.95
        ],
        "Desvios": [
          1.15
        ],
        "DesvioDeNotas": 0,
        "MediaDeNotas": 9.95,
        "MediaDeDesvios": 1.15,
        "NotaMediana": 9.95
      },
      "ADM0067 - NOVAS TECNOLOGIAS NA GESTÃO PÚBLICA": {
        "Notas": [
          9.87
        ],
        "Desvios": [
          0.9
        ],
        "DesvioDeNotas": 0,
        "MediaDeNotas": 9.87,
        "MediaDeDesvios": 0.9,
        "NotaMediana": 9.87
      },
      "ADM0074 - TEORIA GERAL DAS ORGANIZAÇÕES": {
        "Notas": [
          9.9
        ],
        "Desvios": [
          1.09
        ],
        "DesvioDeNotas": 0,
        "MediaDeNotas": 9.9,
        "MediaDeDesvios": 1.09,
        "NotaMediana": 9.9
      }
    },
    "DesvioDeNotas": 0.02947456530637885,
    "MediaDeNotas": 9.9025,
    "MediaDeDesvios": 1.1025,
    "NotaMediana": 9.9
  },
  "JOANNES EMMANUEL DANTAS E RODRIGUES DE LIMA": {
    "Notas": [
      8.56,
      8.9,
      9,
      9.25
    ],
    "Desvios": [
      1.26,
      1.56,
      1.64,
      1.87
    ],
    "Componentes": {
      "ADM0523 - EMPREENDEDORISMO E PLANO DE NEGÓCIOS": {
        "Notas": [
          9.25
        ],
        "Desvios": [
          1.26
        ],
        "DesvioDeNotas": 0,
        "MediaDeNotas": 9.25,
        "MediaDeDesvios": 1.26,
        "NotaMediana": 9.25
      },
      "ADM0541 - GESTAO DE PESSOAS I": {
        "Notas": [
          9
        ],
        "Desvios": [
          1.56
        ],
        "DesvioDeNotas": 0,
        "MediaDeNotas": 9,
        "MediaDeDesvios": 1.56,
        "NotaMediana": 9
      },
      "ADM0542 - GESTAO DE PESSOAS II": {
        "Notas": [
          8.9
        ],
        "Desvios": [
          1.64
        ],
        "DesvioDeNotas": 0,
        "MediaDeNotas": 8.9,
        "MediaDeDesvios": 1.64,
        "NotaMediana": 8.9
      },
      "ADM0075 - ORGANIZAÇÃO, PROCESSOS E SISTEMAS": {
        "Notas": [
          8.56
        ],
        "Desvios": [
          1.87
        ],
        "DesvioDeNotas": 0,
        "MediaDeNotas": 8.56,
        "MediaDeDesvios": 1.87,
        "NotaMediana": 8.56
      }
    },
    "DesvioDeNotas": 0.24752525123712105,
    "MediaDeNotas": 8.9275,
    "MediaDeDesvios": 1.5825,
    "NotaMediana": 9
  },
  "LUCIANO MENEZES BEZERRA SAMPAIO": {
    "Notas": [
      9.57,
      9.77
    ],
    "Desvios": [
      1.01,
      1.08
    ],
    "Componentes": {
      "ADM0069 - NOÇÕES DE PESQUISA OPERACIONAL": {
        "Notas": [
          9.57,
          9.77
        ],
        "Desvios": [
          1.01,
          1.08
        ],
        "DesvioDeNotas": 0.09999999999999964,
        "MediaDeNotas": 9.67,
        "MediaDeDesvios": 1.045,
        "NotaMediana": 9.77
      }
    },
    "DesvioDeNotas": 0.09999999999999964,
    "MediaDeNotas": 9.67,
    "MediaDeDesvios": 1.045,
    "NotaMediana": 9.77
  },
  "RAONI FERNANDES AZEREDO": {
    "Notas": [
      9.59,
      9.79
    ],
    "Desvios": [
      1,
      1.32
    ],
    "Componentes": {
      "COP0035 - ELABORAÇÃO DE PROJETO I": {
        "Notas": [
          9.59
        ],
        "Desvios": [
          1
        ],
        "DesvioDeNotas": 0,
        "MediaDeNotas": 9.59,
        "MediaDeDesvios": 1,
        "NotaMediana": 9.59
      },
      "ADM0062 - GESTÃO DE EMPREENDIMENTOS ECONÔMICO-SOLIDÁRIOS": {
        "Notas": [
          9.79
        ],
        "Desvios": [
          1.32
        ],
        "DesvioDeNotas": 0,
        "MediaDeNotas": 9.79,
        "MediaDeDesvios": 1.32,
        "NotaMediana": 9.79
      }
    },
    "DesvioDeNotas": 0.09999999999999964,
    "MediaDeNotas": 9.69,
    "MediaDeDesvios": 1.1600000000000001,
    "NotaMediana": 9.79
  },
  "RENAN FELINTO DE FARIAS AIRES": {
    "Notas": [
      9.02,
      9.57,
      9.73,
      9.89
    ],
    "Desvios": [
      1.52,
      1.06,
      1.5,
      1.19
    ],
    "Componentes": {
      "ADM0425 - ADMINISTRACAO DA PRODUCAO II": {
        "Notas": [
          9.57
        ],
        "Desvios": [
          1.52
        ],
        "DesvioDeNotas": 0,
        "MediaDeNotas": 9.57,
        "MediaDeDesvios": 1.52,
        "NotaMediana": 9.57
      },
      "ADM0523 - EMPREENDEDORISMO E PLANO DE NEGÓCIOS": {
        "Notas": [
          9.89
        ],
        "Desvios": [
          1.06
        ],
        "DesvioDeNotas": 0,
        "MediaDeNotas": 9.89,
        "MediaDeDesvios": 1.06,
        "NotaMediana": 9.89
      },
      "ADM0058 - GESTÃO DE SISTEMA DE INFORMAÇÃO": {
        "Notas": [
          9.02
        ],
        "Desvios": [
          1.5
        ],
        "DesvioDeNotas": 0,
        "MediaDeNotas": 9.02,
        "MediaDeDesvios": 1.5,
        "NotaMediana": 9.02
      },
      "ADM0518 - SISTEMAS DE GESTAO DA QUALIDADE": {
        "Notas": [
          9.73
        ],
        "Desvios": [
          1.19
        ],
        "DesvioDeNotas": 0,
        "MediaDeNotas": 9.73,
        "MediaDeDesvios": 1.19,
        "NotaMediana": 9.73
      }
    },
    "DesvioDeNotas": 0.32759540595069436,
    "MediaDeNotas": 9.5525,
    "MediaDeDesvios": 1.3175,
    "NotaMediana": 9.73
  },
  "VICENTE MORO": {
    "Notas": [
      8.25,
      9.35,
      9.5
    ],
    "Desvios": [
      1.66,
      1.72,
      2.03
    ],
    "Componentes": {
      "ADM0500 - METODOLOGIA CIENTIFICA E PESQUISA EM ADMINISTRACAO": {
        "Notas": [
          9.35,
          9.5
        ],
        "Desvios": [
          1.66,
          1.72
        ],
        "DesvioDeNotas": 0.07500000000000018,
        "MediaDeNotas": 9.425,
        "MediaDeDesvios": 1.69,
        "NotaMediana": 9.5
      },
      "ADM0135 - OFICINA DE PROJETO II": {
        "Notas": [
          8.25
        ],
        "Desvios": [
          2.03
        ],
        "DesvioDeNotas": 0,
        "MediaDeNotas": 8.25,
        "MediaDeDesvios": 2.03,
        "NotaMediana": 8.25
      }
    },
    "DesvioDeNotas": 0.5572751165766828,
    "MediaDeNotas": 9.033333333333333,
    "MediaDeDesvios": 1.8033333333333335,
    "NotaMediana": 9.35
  }
}